{"inkVersion":21,"root":[["^Hey, [Player Name]! Long time no see. Mind if I chill with you for a bit?\"","\n",["ev",{"^->":"0.2.$r1"},{"temp=":"$r"},"str",{"->":".^.s"},[{"#n":"$r1"}],"/str","/ev",{"*":"0.c-0","flg":18},{"s":["^Sure, Kai. It's been a while.",{"->":"$r","var":true},null]}],["ev",{"^->":"0.3.$r1"},{"temp=":"$r"},"str",{"->":".^.s"},[{"#n":"$r1"}],"/str","/ev",{"*":"0.c-1","flg":18},{"s":["^Uh, yeah, of course.",{"->":"$r","var":true},null]}],["ev",{"^->":"0.4.$r1"},{"temp=":"$r"},"str",{"->":".^.s"},[{"#n":"$r1"}],"/str","/ev",{"*":"0.c-2","flg":18},{"s":["^Nod hesitantly",{"->":"$r","var":true},null]}],{"c-0":["ev",{"^->":"0.c-0.$r2"},"/ev",{"temp=":"$r"},{"->":"0.2.s"},[{"#n":"$r2"}],{"->":"CG_one"},"\n",{"->":"0.g-0"},{"#f":5}],"c-1":["ev",{"^->":"0.c-1.$r2"},"/ev",{"temp=":"$r"},{"->":"0.3.s"},[{"#n":"$r2"}],{"->":"CG_one"},"\n",{"->":"0.g-0"},{"#f":5}],"c-2":["ev",{"^->":"0.c-2.$r2"},"/ev",{"temp=":"$r"},{"->":"0.4.s"},[{"#n":"$r2"}],{"->":"CG_one"},"\n",{"->":"0.g-0"},{"#f":5}],"g-0":["done",{"#f":5}]}],"done",{"CG_one":[["^Thanks. This party is pretty awesome. You did a great job putting it together. So, how have you been? It's really been ages since we last talked.","\n",["ev",{"^->":"CG_one.0.2.$r1"},{"temp=":"$r"},"str",{"->":".^.s"},[{"#n":"$r1"}],"/str","/ev",{"*":".^.^.c-0","flg":18},{"s":["^I've been okay, just busy with life.\" ",{"->":"$r","var":true},null]}],["ev",{"^->":"CG_one.0.3.$r1"},{"temp=":"$r"},"str",{"->":".^.s"},[{"#n":"$r1"}],"/str","/ev",{"*":".^.^.c-1","flg":18},{"s":["^It's been rough, but I'm getting by.\" ",{"->":"$r","var":true},null]}],["ev",{"^->":"CG_one.0.4.$r1"},{"temp=":"$r"},"str",{"->":".^.s"},[{"#n":"$r1"}],"/str","/ev",{"*":".^.^.c-2","flg":18},{"s":["^Not great, to be honest ",{"->":"$r","var":true},null]}],{"c-0":["ev",{"^->":"CG_one.0.c-0.$r2"},"/ev",{"temp=":"$r"},{"->":".^.^.2.s"},[{"#n":"$r2"}],{"->":"CG_two"},"\n",{"#f":5}],"c-1":["ev",{"^->":"CG_one.0.c-1.$r2"},"/ev",{"temp=":"$r"},{"->":".^.^.3.s"},[{"#n":"$r2"}],{"->":"CG_two"},"\n",{"#f":5}],"c-2":["ev",{"^->":"CG_one.0.c-2.$r2"},"/ev",{"temp=":"$r"},{"->":".^.^.4.s"},[{"#n":"$r2"}],{"->":"CG_two"},"\n",{"#f":5}]}],{"#f":1}],"CG_two":[["^I get that. Life can be a rollercoaster sometimes. You know, it's really nice to see you here, socializing. It can be tough getting out there, right?","\n",["ev",{"^->":"CG_two.0.2.$r1"},{"temp=":"$r"},"str",{"->":".^.s"},[{"#n":"$r1"}],"/str","/ev",{"*":".^.^.c-0","flg":18},{"s":["^Yeah, it's been a challenge lately.\" ",{"->":"$r","var":true},null]}],["ev",{"^->":"CG_two.0.3.$r1"},{"temp=":"$r"},"str",{"->":".^.s"},[{"#n":"$r1"}],"/str","/ev",{"*":".^.^.c-1","flg":18},{"s":["^I'm trying, but it's not easy.\" ",{"->":"$r","var":true},null]}],["ev",{"^->":"CG_two.0.4.$r1"},{"temp=":"$r"},"str",{"->":".^.s"},[{"#n":"$r1"}],"/str","/ev",{"*":".^.^.c-2","flg":18},{"s":["^I almost didn't come tonight.\" ",{"->":"$r","var":true},null]}],{"c-0":["ev",{"^->":"CG_two.0.c-0.$r2"},"/ev",{"temp=":"$r"},{"->":".^.^.2.s"},[{"#n":"$r2"}],{"->":"CG_three"},"\n",{"#f":5}],"c-1":["ev",{"^->":"CG_two.0.c-1.$r2"},"/ev",{"temp=":"$r"},{"->":".^.^.3.s"},[{"#n":"$r2"}],{"->":"CG_three"},"\n",{"#f":5}],"c-2":["ev",{"^->":"CG_two.0.c-2.$r2"},"/ev",{"temp=":"$r"},{"->":".^.^.4.s"},[{"#n":"$r2"}],{"->":"CG_three"},"\n",{"#f":5}]}],{"#f":1}],"CG_three":[["^Well, I'm glad you did. It's good to catch up. So, tell me, what have you been up to these days? Any new hobbies or interests?","\n",["ev",{"^->":"CG_three.0.2.$r1"},{"temp=":"$r"},"str",{"->":".^.s"},[{"#n":"$r1"}],"/str","/ev",{"*":".^.^.c-0","flg":18},{"s":["^Not really. Just trying to get through each day.\" ",{"->":"$r","var":true},null]}],["ev",{"^->":"CG_three.0.3.$r1"},{"temp=":"$r"},"str",{"->":".^.s"},[{"#n":"$r1"}],"/str","/ev",{"*":".^.^.c-1","flg":18},{"s":["^I've picked up a bit of gaming again.\" ",{"->":"$r","var":true},null]}],["ev",{"^->":"CG_three.0.4.$r1"},{"temp=":"$r"},"str",{"->":".^.s"},[{"#n":"$r1"}],"/str","/ev",{"*":".^.^.c-2","flg":18},{"s":["^\"I'm not sure. I haven't felt like doing much.",{"->":"$r","var":true},null]}],{"c-0":["ev",{"^->":"CG_three.0.c-0.$r2"},"/ev",{"temp=":"$r"},{"->":".^.^.2.s"},[{"#n":"$r2"}],{"->":"CG_four"},"\n",{"#f":5}],"c-1":["ev",{"^->":"CG_three.0.c-1.$r2"},"/ev",{"temp=":"$r"},{"->":".^.^.3.s"},[{"#n":"$r2"}],{"->":"CG_four"},"\n",{"#f":5}],"c-2":["ev",{"^->":"CG_three.0.c-2.$r2"},"/ev",{"temp=":"$r"},{"->":".^.^.4.s"},[{"#n":"$r2"}],{"->":"CG_four"},"\n",{"#f":5}]}],{"#f":1}],"CG_four":[["^Gaming? That's awesome! What kind of games are you into these days?\"","\n",["ev",{"^->":"CG_four.0.2.$r1"},{"temp=":"$r"},"str",{"->":".^.s"},[{"#n":"$r1"}],"/str","/ev",{"*":".^.^.c-0","flg":18},{"s":["^\"Mostly RPGs, but I'm open to anything.\" ",{"->":"$r","var":true},null]}],["ev",{"^->":"CG_four.0.3.$r1"},{"temp=":"$r"},"str",{"->":".^.s"},[{"#n":"$r1"}],"/str","/ev",{"*":".^.^.c-1","flg":18},{"s":["^\"I enjoy action and adventure games.\" ",{"->":"$r","var":true},null]}],["ev",{"^->":"CG_four.0.4.$r1"},{"temp=":"$r"},"str",{"->":".^.s"},[{"#n":"$r1"}],"/str","/ev",{"*":".^.^.c-2","flg":18},{"s":["^\"I haven't really settled on a favorite genre.\" ",{"->":"$r","var":true},null]}],{"c-0":["ev",{"^->":"CG_four.0.c-0.$r2"},"/ev",{"temp=":"$r"},{"->":".^.^.2.s"},[{"#n":"$r2"}],{"->":"CG_Five"},"\n",{"#f":5}],"c-1":["ev",{"^->":"CG_four.0.c-1.$r2"},"/ev",{"temp=":"$r"},{"->":".^.^.3.s"},[{"#n":"$r2"}],{"->":"CG_Five"},"\n",{"#f":5}],"c-2":["ev",{"^->":"CG_four.0.c-2.$r2"},"/ev",{"temp=":"$r"},{"->":".^.^.4.s"},[{"#n":"$r2"}],{"->":"CG_Five"},"\n",{"#f":5}]}],{"#f":1}],"CG_Five":[["^RPGs are great for immersing yourself in a different world, and action-adventure games are always a blast. Do you have a favorite game right now?","\n",["ev",{"^->":"CG_Five.0.2.$r1"},{"temp=":"$r"},"str",{"->":".^.s"},[{"#n":"$r1"}],"/str","/ev",{"*":".^.^.c-0","flg":18},{"s":["^\"Not really. There are so many good ones.\" ",{"->":"$r","var":true},null]}],["ev",{"^->":"CG_Five.0.3.$r1"},{"temp=":"$r"},"str",{"->":".^.s"},[{"#n":"$r1"}],"/str","str","^Game Title","/str","/ev",{"*":".^.^.c-1","flg":22},{"s":["^\"I think I'd go with ",{"->":"$r","var":true},null]}],["ev",{"^->":"CG_Five.0.4.$r1"},{"temp=":"$r"},"str",{"->":".^.s"},[{"#n":"$r1"}],"/str","/ev",{"*":".^.^.c-2","flg":18},{"s":["^\"I haven't found one that stands out yet.\"",{"->":"$r","var":true},null]}],{"c-0":["ev",{"^->":"CG_Five.0.c-0.$r2"},"/ev",{"temp=":"$r"},{"->":".^.^.2.s"},[{"#n":"$r2"}],{"->":"CG_Six"},"\n",{"#f":5}],"c-1":["ev",{"^->":"CG_Five.0.c-1.$r2"},"/ev",{"temp=":"$r"},{"->":".^.^.3.s"},[{"#n":"$r2"}],"^.\"",{"->":"CG_Six"},"\n",{"#f":5}],"c-2":["ev",{"^->":"CG_Five.0.c-2.$r2"},"/ev",{"temp=":"$r"},{"->":".^.^.4.s"},[{"#n":"$r2"}],{"->":"CG_Six"},"\n",{"#f":5}]}],{"#f":1}],"CG_Six":[["^You're doing great. Seriously. Sometimes it's just about showing up and being present. So, what else is new with you? Anything exciting coming up","\n",["ev",{"^->":"CG_Six.0.2.$r1"},{"temp=":"$r"},"str",{"->":".^.s"},[{"#n":"$r1"}],"/str","/ev",{"*":".^.^.c-0","flg":18},{"s":["^\"Not much. Just taking things day by day.\"",{"->":"$r","var":true},null]}],["ev",{"^->":"CG_Six.0.3.$r1"},{"temp=":"$r"},"str",{"->":".^.s"},[{"#n":"$r1"}],"/str","/ev",{"*":".^.^.c-1","flg":18},{"s":["^\"I have a few projects I'm working on.\"",{"->":"$r","var":true},null]}],["ev",{"^->":"CG_Six.0.4.$r1"},{"temp=":"$r"},"str",{"->":".^.s"},[{"#n":"$r1"}],"/str","/ev",{"*":".^.^.c-2","flg":18},{"s":["^\"I'm hoping to start something new soon.\"",{"->":"$r","var":true},null]}],{"c-0":["ev",{"^->":"CG_Six.0.c-0.$r2"},"/ev",{"temp=":"$r"},{"->":".^.^.2.s"},[{"#n":"$r2"}],{"->":"CG_Seven"},"\n",{"#f":5}],"c-1":["ev",{"^->":"CG_Six.0.c-1.$r2"},"/ev",{"temp=":"$r"},{"->":".^.^.3.s"},[{"#n":"$r2"}],{"->":"CG_Seven"},"\n",{"#f":5}],"c-2":["ev",{"^->":"CG_Six.0.c-2.$r2"},"/ev",{"temp=":"$r"},{"->":".^.^.4.s"},[{"#n":"$r2"}],{"->":"CG_Seven"},"\n",{"#f":5}]}],{"#f":1}],"CG_Seven":["^That sounds good. Taking it day by day is all you can do sometimes. And new projects can be really invigorating. Just remember, it's all about balance. Don't be too hard on yourself.\"","\n","^A) \"I'll try to keep that in mind.\" ",{"->":"CG_Eight"},"\n","^B) \"Thanks for the advice.\" ",{"->":".^"},"\n","^C) \"It's tough, but I'll do my best.\" ",{"->":"CG_Eight"},"\n",{"#f":1}],"CG_Eight":["^You're doing just fine. And hey, if you ever need someone to talk to or just hang out with, I'm here. We should definitely catch up more often.","\n","^A) \"I'd like that. Thanks, Kai.\" ",{"->":".^"},"\n","^B) \"Yeah, that would be nice.\" ",{"->":".^"},"\n","^C) Smile and nod appreciatively ",{"->":".^"},"\n",{"#f":1}],"CG_Nine":["^\"Great! Let's enjoy the rest of the party and catch up some more. It's really good to see you again, [Player Name].\"","\n","end",{"#f":1}],"#f":1}],"listDefs":{}}